cursed_geobr-0.1.7.dist-info/METADATA
cursed_geobr-0.1.7.dist-info/WHEEL
cursed_geobr-0.1.7.dist-info/entry_points.txt
cursed_geobr-0.1.7.dist-info/licenses/LICENSE.txt
cursed_geobr/__init__.py
cursed_geobr/constants.py
cursed_geobr/data/grid_state_correspondence_table.csv
cursed_geobr/list_geobr.py
cursed_geobr/lookup_muni.py
cursed_geobr/read_amazon.py
cursed_geobr/read_amazon_ibas.py
cursed_geobr/read_atlantic_forest_ibas.py
cursed_geobr/read_biomes.py
cursed_geobr/read_census_tract.py
cursed_geobr/read_climate_aggressiveness.py
cursed_geobr/read_comparable_areas.py
cursed_geobr/read_conservation_units.py
cursed_geobr/read_country.py
cursed_geobr/read_disaster_risk_area.py
cursed_geobr/read_geology.py
cursed_geobr/read_geomorphology.py
cursed_geobr/read_health_facilities.py
cursed_geobr/read_health_region.py
cursed_geobr/read_immediate_region.py
cursed_geobr/read_indigenous_land.py
cursed_geobr/read_intermediate_region.py
cursed_geobr/read_meso_region.py
cursed_geobr/read_metro_area.py
cursed_geobr/read_micro_region.py
cursed_geobr/read_mining_processes.py
cursed_geobr/read_municipal_seat.py
cursed_geobr/read_municipality.py
cursed_geobr/read_neighborhood.py
cursed_geobr/read_pedology.py
cursed_geobr/read_pop_arrangements.py
cursed_geobr/read_region.py
cursed_geobr/read_schools.py
cursed_geobr/read_semiarid.py
cursed_geobr/read_settlements.py
cursed_geobr/read_state.py
cursed_geobr/read_statistical_grid.py
cursed_geobr/read_urban_area.py
cursed_geobr/read_urban_concentrations.py
cursed_geobr/read_weighting_area.py
cursed_geobr/utils.py
cursed_geobr-0.1.7.dist-info/RECORD
