Metadata-Version: 2.1
Name: cursed-geobr
Version: 0.1.7
Summary: Fork personalizado do geobr com funcionalidades extras como download de dados da ANM
Author: Anderson Stolfi
License: MIT
Classifier: Intended Audience :: Science/Research
Classifier: Intended Audience :: Developers
Classifier: Intended Audience :: Education
Classifier: Topic :: Scientific/Engineering :: GIS
Classifier: Topic :: Scientific/Engineering :: Visualization
Classifier: Programming Language :: Python
Project-URL: homepage, https://github.com/popogis24/cursed_geobr
Project-URL: repository, https://github.com/popogis24/cursed_geobr
Requires-Python: <4.0,>=3.9
Requires-Dist: geopandas<=1.1,>=1.0.0
Requires-Dist: shapely<=2.1.0,>=1.7.0
Requires-Dist: requests<3.0.0,>=2.25.1
Requires-Dist: lxml<6.0.0,>=5.1.0
Requires-Dist: html5lib==1.1
Requires-Dist: geobr<0.3.0,>=0.2.2
Requires-Dist: patool>=1.15.0
